tap_zammad/__init__.py
tap_zammad/client.py
tap_zammad/paginators.py
tap_zammad/streams.py
tap_zammad/tap.py
tap_zammad/tests/__init__.py
tap_zammad/tests/test_core.py
tap_zammad-0.0.5.dist-info/WHEEL
tap_zammad-0.0.5.dist-info/entry_points.txt
tap_zammad-0.0.5.dist-info/METADATA
tap_zammad-0.0.5.dist-info/RECORD
