Metadata-Version: 2.1
Name: tap-zammad
Version: 0.0.5
Summary: tap-zammad is a Singer tap for Zammad, built with the Meltano SDK for Singer Taps.
License: Apache 2.0
Keywords: ELT,Zammad
Author: Luis Ventura
Requires-Python: >=3.8.1,<3.11
Classifier: License :: Other/Proprietary License
Classifier: Programming Language :: Python :: 3
Classifier: Programming Language :: Python :: 3.9
Classifier: Programming Language :: Python :: 3.10
Requires-Dist: requests (>=2.25.1,<3.0.0)
Requires-Dist: singer-sdk (>=0.20.0,<0.21.0)
